[
  {
    "inputs": [
      {
        "internalType": "address",
        "name": "_etkTokenAddress",
        "type": "address"
      }
    ],
    "stateMutability": "nonpayable",
    "type": "constructor"
  },
  {
    "inputs": [],
    "name": "BelowMinimumThreshold",
    "type": "error"
  },
  {
    "inputs": [],
    "name": "InsufficientBalance",
    "type": "error"
  },
  {
    "inputs": [],
    "name": "InvalidAddress",
    "type": "error"
  },
  {
    "inputs": [],
    "name": "InvalidMeterId",
    "type": "error"
  },
  {
    "inputs": [],
    "name": "NotAuthorizedMeter",
    "type": "error"
  },
  {
    "inputs": [],
    "name": "NotOwner",
    "type": "error"
  },
  {
    "inputs": [],
    "name": "SettlementAlreadyProcessed",
    "type": "error"
  },
  {
    "inputs": [],
    "name": "TransferFailed",
    "type": "error"
  },
  {
    "anonymous": false,
    "inputs": [
      {
        "indexed": false,
        "internalType": "uint256",
        "name": "oldRatio",
        "type": "uint256"
      },
      {
        "indexed": false,
        "internalType": "uint256",
        "name": "newRatio",
        "type": "uint256"
      },
      {
        "indexed": false,
        "internalType": "address",
        "name": "updatedBy",
        "type": "address"
      }
    ],
    "name": "ConversionRatioUpdated",
    "type": "event"
  },
  {
    "anonymous": false,
    "inputs": [
      {
        "indexed": false,
        "internalType": "string",
        "name": "meterId",
        "type": "string"
      },
      {
        "indexed": false,
        "internalType": "address",
        "name": "meterAddress",
        "type": "address"
      },
      {
        "indexed": false,
        "internalType": "address",
        "name": "authorizedBy",
        "type": "address"
      }
    ],
    "name": "MeterAuthorized",
    "type": "event"
  },
  {
    "anonymous": false,
    "inputs": [
      {
        "indexed": false,
        "internalType": "string",
        "name": "meterId",
        "type": "string"
      },
      {
        "indexed": false,
        "internalType": "address",
        "name": "meterAddress",
        "type": "address"
      },
      {
        "indexed": false,
        "internalType": "address",
        "name": "deauthorizedBy",
        "type": "address"
      }
    ],
    "name": "MeterDeauthorized",
    "type": "event"
  },
  {
    "anonymous": false,
    "inputs": [
      {
        "indexed": false,
        "internalType": "uint256",
        "name": "oldMinWh",
        "type": "uint256"
      },
      {
        "indexed": false,
        "internalType": "uint256",
        "name": "newMinWh",
        "type": "uint256"
      },
      {
        "indexed": false,
        "internalType": "address",
        "name": "updatedBy",
        "type": "address"
      }
    ],
    "name": "MinSettlementUpdated",
    "type": "event"
  },
  {
    "anonymous": false,
    "inputs": [
      {
        "indexed": true,
        "internalType": "bytes32",
        "name": "settlementId",
        "type": "bytes32"
      },
      {
        "indexed": true,
        "internalType": "string",
        "name": "meterId",
        "type": "string"
      },
      {
        "indexed": true,
        "internalType": "address",
        "name": "prosumerAddress",
        "type": "address"
      },
      {
        "indexed": false,
        "internalType": "int256",
        "name": "netEnergyWh",
        "type": "int256"
      },
      {
        "indexed": false,
        "internalType": "uint256",
        "name": "etkAmount",
        "type": "uint256"
      },
      {
        "indexed": false,
        "internalType": "uint256",
        "name": "timestamp",
        "type": "uint256"
      }
    ],
    "name": "SettlementProcessed",
    "type": "event"
  },
  {
    "inputs": [
      {
        "internalType": "string",
        "name": "_meterId",
        "type": "string"
      },
      {
        "internalType": "address",
        "name": "_meterAddress",
        "type": "address"
      }
    ],
    "name": "authorizeMeter",
    "outputs": [],
    "stateMutability": "nonpayable",
    "type": "function"
  },
  {
    "inputs": [
      {
        "internalType": "string",
        "name": "",
        "type": "string"
      }
    ],
    "name": "authorizedMeterIds",
    "outputs": [
      {
        "internalType": "bool",
        "name": "",
        "type": "bool"
      }
    ],
    "stateMutability": "view",
    "type": "function"
  },
  {
    "inputs": [
      {
        "internalType": "address",
        "name": "",
        "type": "address"
      }
    ],
    "name": "authorizedMeters",
    "outputs": [
      {
        "internalType": "bool",
        "name": "",
        "type": "bool"
      }
    ],
    "stateMutability": "view",
    "type": "function"
  },
  {
    "inputs": [
      {
        "internalType": "uint256",
        "name": "_etkAmount",
        "type": "uint256"
      }
    ],
    "name": "calculateEnergyWh",
    "outputs": [
      {
        "internalType": "uint256",
        "name": "",
        "type": "uint256"
      }
    ],
    "stateMutability": "view",
    "type": "function"
  },
  {
    "inputs": [
      {
        "internalType": "uint256",
        "name": "_energyWh",
        "type": "uint256"
      }
    ],
    "name": "calculateEtkAmount",
    "outputs": [
      {
        "internalType": "uint256",
        "name": "",
        "type": "uint256"
      }
    ],
    "stateMutability": "view",
    "type": "function"
  },
  {
    "inputs": [],
    "name": "conversionRatio",
    "outputs": [
      {
        "internalType": "uint256",
        "name": "",
        "type": "uint256"
      }
    ],
    "stateMutability": "view",
    "type": "function"
  },
  {
    "inputs": [
      {
        "internalType": "string",
        "name": "_meterId",
        "type": "string"
      },
      {
        "internalType": "address",
        "name": "_meterAddress",
        "type": "address"
      }
    ],
    "name": "deauthorizeMeter",
    "outputs": [],
    "stateMutability": "nonpayable",
    "type": "function"
  },
  {
    "inputs": [
      {
        "internalType": "uint256",
        "name": "_amount",
        "type": "uint256"
      }
    ],
    "name": "emergencyWithdrawETK",
    "outputs": [],
    "stateMutability": "nonpayable",
    "type": "function"
  },
  {
    "inputs": [],
    "name": "etk_token",
    "outputs": [
      {
        "internalType": "contract ETK",
        "name": "",
        "type": "address"
      }
    ],
    "stateMutability": "view",
    "type": "function"
  },
  {
    "inputs": [
      {
        "internalType": "bytes32",
        "name": "_settlementId",
        "type": "bytes32"
      }
    ],
    "name": "getSettlement",
    "outputs": [
      {
        "internalType": "string",
        "name": "meterId",
        "type": "string"
      },
      {
        "internalType": "address",
        "name": "prosumerAddress",
        "type": "address"
      },
      {
        "internalType": "int256",
        "name": "netEnergyWh",
        "type": "int256"
      },
      {
        "internalType": "uint256",
        "name": "etkAmount",
        "type": "uint256"
      },
      {
        "internalType": "uint256",
        "name": "timestamp",
        "type": "uint256"
      },
      {
        "internalType": "bool",
        "name": "processed",
        "type": "bool"
      }
    ],
    "stateMutability": "view",
    "type": "function"
  },
  {
    "inputs": [],
    "name": "getSettlementCount",
    "outputs": [
      {
        "internalType": "uint256",
        "name": "",
        "type": "uint256"
      }
    ],
    "stateMutability": "view",
    "type": "function"
  },
  {
    "inputs": [
      {
        "internalType": "uint256",
        "name": "_index",
        "type": "uint256"
      }
    ],
    "name": "getSettlementIdByIndex",
    "outputs": [
      {
        "internalType": "bytes32",
        "name": "",
        "type": "bytes32"
      }
    ],
    "stateMutability": "view",
    "type": "function"
  },
  {
    "inputs": [
      {
        "internalType": "address",
        "name": "_meterAddress",
        "type": "address"
      }
    ],
    "name": "isMeterAuthorized",
    "outputs": [
      {
        "internalType": "bool",
        "name": "",
        "type": "bool"
      }
    ],
    "stateMutability": "view",
    "type": "function"
  },
  {
    "inputs": [
      {
        "internalType": "string",
        "name": "_meterId",
        "type": "string"
      }
    ],
    "name": "isMeterIdAuthorized",
    "outputs": [
      {
        "internalType": "bool",
        "name": "",
        "type": "bool"
      }
    ],
    "stateMutability": "view",
    "type": "function"
  },
  {
    "inputs": [],
    "name": "minSettlementWh",
    "outputs": [
      {
        "internalType": "uint256",
        "name": "",
        "type": "uint256"
      }
    ],
    "stateMutability": "view",
    "type": "function"
  },
  {
    "inputs": [],
    "name": "owner",
    "outputs": [
      {
        "internalType": "address",
        "name": "",
        "type": "address"
      }
    ],
    "stateMutability": "view",
    "type": "function"
  },
  {
    "inputs": [
      {
        "internalType": "string",
        "name": "_meterId",
        "type": "string"
      },
      {
        "internalType": "address",
        "name": "_prosumerAddress",
        "type": "address"
      },
      {
        "internalType": "int256",
        "name": "_netEnergyWh",
        "type": "int256"
      },
      {
        "internalType": "bytes32",
        "name": "_settlementId",
        "type": "bytes32"
      }
    ],
    "name": "processSettlement",
    "outputs": [
      {
        "internalType": "uint256",
        "name": "",
        "type": "uint256"
      }
    ],
    "stateMutability": "nonpayable",
    "type": "function"
  },
  {
    "inputs": [
      {
        "internalType": "uint256",
        "name": "",
        "type": "uint256"
      }
    ],
    "name": "settlementIds",
    "outputs": [
      {
        "internalType": "bytes32",
        "name": "",
        "type": "bytes32"
      }
    ],
    "stateMutability": "view",
    "type": "function"
  },
  {
    "inputs": [
      {
        "internalType": "bytes32",
        "name": "",
        "type": "bytes32"
      }
    ],
    "name": "settlements",
    "outputs": [
      {
        "internalType": "string",
        "name": "meterId",
        "type": "string"
      },
      {
        "internalType": "address",
        "name": "prosumerAddress",
        "type": "address"
      },
      {
        "internalType": "int256",
        "name": "netEnergyWh",
        "type": "int256"
      },
      {
        "internalType": "uint256",
        "name": "etkAmount",
        "type": "uint256"
      },
      {
        "internalType": "uint256",
        "name": "timestamp",
        "type": "uint256"
      },
      {
        "internalType": "bool",
        "name": "processed",
        "type": "bool"
      }
    ],
    "stateMutability": "view",
    "type": "function"
  },
  {
    "inputs": [
      {
        "internalType": "address",
        "name": "_newOwner",
        "type": "address"
      }
    ],
    "name": "transferOwnership",
    "outputs": [],
    "stateMutability": "nonpayable",
    "type": "function"
  },
  {
    "inputs": [
      {
        "internalType": "uint256",
        "name": "_newRatio",
        "type": "uint256"
      }
    ],
    "name": "updateConversionRatio",
    "outputs": [],
    "stateMutability": "nonpayable",
    "type": "function"
  },
  {
    "inputs": [
      {
        "internalType": "uint256",
        "name": "_newMinWh",
        "type": "uint256"
      }
    ],
    "name": "updateMinSettlement",
    "outputs": [],
    "stateMutability": "nonpayable",
    "type": "function"
  }
]
